Metadata-Version: 2.1
Name: youtube-search-fork
Version: 1.2.3
Summary: Search on youtube avoiding the use their heavily rate-limited API. Fork of original youtube-search by joetats
Home-page: https://github.com/pluja/youtube_search-fork
Author: Pluja
Author-email: pluja@r3d.red
License: MIT
Platform: UNKNOWN
Classifier: License :: OSI Approved :: MIT License
Classifier: Programming Language :: Python :: 3
Classifier: Programming Language :: Python :: 3.7
Classifier: Programming Language :: Python :: 3.8
